{"nodes": [{"id": "flashscore_pipeline_protocol_py", "label": "protocol.py", "file_type": "code", "source_file": "flashscore_pipeline/protocol.py", "source_location": "L1"}, {"id": "protocol_flashscoreprotocol", "label": "FlashscoreProtocol", "file_type": "code", "source_file": "flashscore_pipeline/protocol.py", "source_location": "L4"}, {"id": "protocol_parse_frame", "label": "parse_frame()", "file_type": "code", "source_file": "flashscore_pipeline/protocol.py", "source_location": "L14"}, {"id": "protocol_decode_message", "label": "decode_message()", "file_type": "code", "source_file": "flashscore_pipeline/protocol.py", "source_location": "L52"}, {"id": "protocol_rationale_5", "label": "Parser for the Flashscore proprietary delimited text protocol.     Delimiters:", "file_type": "rationale", "source_file": "flashscore_pipeline/protocol.py", "source_location": "L5"}, {"id": "protocol_rationale_15", "label": "Translates a raw Flashscore frame into a MatchUpdate object.         Optimized f", "file_type": "rationale", "source_file": "flashscore_pipeline/protocol.py", "source_location": "L15"}, {"id": "protocol_rationale_53", "label": "Splits a WebSocket stream into separate protocol frames.", "file_type": "rationale", "source_file": "flashscore_pipeline/protocol.py", "source_location": "L53"}], "edges": [{"source": "flashscore_pipeline_protocol_py", "target": "time", "relation": "imports", "confidence": "EXTRACTED", "source_file": "flashscore_pipeline/protocol.py", "source_location": "L1", "weight": 1.0}, {"source": "flashscore_pipeline_protocol_py", "target": "flashscore_pipeline_models_py", "relation": "imports_from", "confidence": "EXTRACTED", "source_file": "flashscore_pipeline/protocol.py", "source_location": "L2", "weight": 1.0}, {"source": "flashscore_pipeline_protocol_py", "target": "protocol_flashscoreprotocol", "relation": "contains", "confidence": "EXTRACTED", "source_file": "flashscore_pipeline/protocol.py", "source_location": "L4", "weight": 1.0}, {"source": "flashscore_pipeline_protocol_py", "target": "protocol_parse_frame", "relation": "contains", "confidence": "EXTRACTED", "source_file": "flashscore_pipeline/protocol.py", "source_location": "L14", "weight": 1.0}, {"source": "flashscore_pipeline_protocol_py", "target": "protocol_decode_message", "relation": "contains", "confidence": "EXTRACTED", "source_file": "flashscore_pipeline/protocol.py", "source_location": "L52", "weight": 1.0}, {"source": "protocol_rationale_5", "target": "protocol_flashscoreprotocol", "relation": "rationale_for", "confidence": "EXTRACTED", "source_file": "flashscore_pipeline/protocol.py", "source_location": "L5", "weight": 1.0}, {"source": "protocol_rationale_15", "target": "protocol_flashscoreprotocol_parse_frame", "relation": "rationale_for", "confidence": "EXTRACTED", "source_file": "flashscore_pipeline/protocol.py", "source_location": "L15", "weight": 1.0}, {"source": "protocol_rationale_53", "target": "protocol_flashscoreprotocol_decode_message", "relation": "rationale_for", "confidence": "EXTRACTED", "source_file": "flashscore_pipeline/protocol.py", "source_location": "L53", "weight": 1.0}]}