{"nodes": [{"id": "backtest_inplay_py", "label": "backtest_inplay.py", "file_type": "code", "source_file": "backtest_inplay.py", "source_location": "L1"}, {"id": "backtest_inplay_load_matches", "label": "load_matches()", "file_type": "code", "source_file": "backtest_inplay.py", "source_location": "L59"}, {"id": "backtest_inplay_extract_serve_probs", "label": "extract_serve_probs()", "file_type": "code", "source_file": "backtest_inplay.py", "source_location": "L78"}, {"id": "backtest_inplay_parse_score", "label": "parse_score()", "file_type": "code", "source_file": "backtest_inplay.py", "source_location": "L127"}, {"id": "backtest_inplay_kelly_size", "label": "kelly_size()", "file_type": "code", "source_file": "backtest_inplay.py", "source_location": "L158"}, {"id": "backtest_inplay_simulate_inplay", "label": "simulate_inplay()", "file_type": "code", "source_file": "backtest_inplay.py", "source_location": "L180"}, {"id": "backtest_inplay_build_elo", "label": "build_elo()", "file_type": "code", "source_file": "backtest_inplay.py", "source_location": "L329"}, {"id": "backtest_inplay_main", "label": "main()", "file_type": "code", "source_file": "backtest_inplay.py", "source_location": "L342"}, {"id": "backtest_inplay_rationale_1", "label": "In-Play Markov Backtest ======================== Simulates what the live bot wou", "file_type": "rationale", "source_file": "backtest_inplay.py", "source_location": "L1"}, {"id": "backtest_inplay_rationale_79", "label": "Derive P(winner wins point on own serve) and P(winner wins point on return)", "file_type": "rationale", "source_file": "backtest_inplay.py", "source_location": "L79"}, {"id": "backtest_inplay_rationale_128", "label": "Parse '6-3 7-5' or '6-3 3-6 7-6(4)' into [(6,3),(7,5)] etc.     Returns list of", "file_type": "rationale", "source_file": "backtest_inplay.py", "source_location": "L128"}, {"id": "backtest_inplay_rationale_181", "label": "For each match:        - Replay game-by-game score through LiveMatchState", "file_type": "rationale", "source_file": "backtest_inplay.py", "source_location": "L181"}], "edges": [{"source": "backtest_inplay_py", "target": "os", "relation": "imports", "confidence": "EXTRACTED", "source_file": "backtest_inplay.py", "source_location": "L19", "weight": 1.0}, {"source": "backtest_inplay_py", "target": "glob", "relation": "imports", "confidence": "EXTRACTED", "source_file": "backtest_inplay.py", "source_location": "L20", "weight": 1.0}, {"source": "backtest_inplay_py", "target": "json", "relation": "imports", "confidence": "EXTRACTED", "source_file": "backtest_inplay.py", "source_location": "L21", "weight": 1.0}, {"source": "backtest_inplay_py", "target": "logging", "relation": "imports", "confidence": "EXTRACTED", "source_file": "backtest_inplay.py", "source_location": "L22", "weight": 1.0}, {"source": "backtest_inplay_py", "target": "warnings", "relation": "imports", "confidence": "EXTRACTED", "source_file": "backtest_inplay.py", "source_location": "L23", "weight": 1.0}, {"source": "backtest_inplay_py", "target": "sys", "relation": "imports", "confidence": "EXTRACTED", "source_file": "backtest_inplay.py", "source_location": "L24", "weight": 1.0}, {"source": "backtest_inplay_py", "target": "numpy", "relation": "imports", "confidence": "EXTRACTED", "source_file": "backtest_inplay.py", "source_location": "L25", "weight": 1.0}, {"source": "backtest_inplay_py", "target": "pandas", "relation": "imports", "confidence": "EXTRACTED", "source_file": "backtest_inplay.py", "source_location": "L26", "weight": 1.0}, {"source": "backtest_inplay_py", "target": "markov_engine", "relation": "imports_from", "confidence": "EXTRACTED", "source_file": "backtest_inplay.py", "source_location": "L30", "weight": 1.0}, {"source": "backtest_inplay_py", "target": "backtest_inplay_load_matches", "relation": "contains", "confidence": "EXTRACTED", "source_file": "backtest_inplay.py", "source_location": "L59", "weight": 1.0}, {"source": "backtest_inplay_py", "target": "backtest_inplay_extract_serve_probs", "relation": "contains", "confidence": "EXTRACTED", "source_file": "backtest_inplay.py", "source_location": "L78", "weight": 1.0}, {"source": "backtest_inplay_py", "target": "backtest_inplay_parse_score", "relation": "contains", "confidence": "EXTRACTED", "source_file": "backtest_inplay.py", "source_location": "L127", "weight": 1.0}, {"source": "backtest_inplay_py", "target": "backtest_inplay_kelly_size", "relation": "contains", "confidence": "EXTRACTED", "source_file": "backtest_inplay.py", "source_location": "L158", "weight": 1.0}, {"source": "backtest_inplay_py", "target": "backtest_inplay_simulate_inplay", "relation": "contains", "confidence": "EXTRACTED", "source_file": "backtest_inplay.py", "source_location": "L180", "weight": 1.0}, {"source": "backtest_inplay_py", "target": "backtest_inplay_build_elo", "relation": "contains", "confidence": "EXTRACTED", "source_file": "backtest_inplay.py", "source_location": "L329", "weight": 1.0}, {"source": "backtest_inplay_py", "target": "backtest_inplay_main", "relation": "contains", "confidence": "EXTRACTED", "source_file": "backtest_inplay.py", "source_location": "L342", "weight": 1.0}, {"source": "backtest_inplay_simulate_inplay", "target": "backtest_inplay_parse_score", "relation": "calls", "confidence": "EXTRACTED", "source_file": "backtest_inplay.py", "source_location": "L197", "weight": 1.0}, {"source": "backtest_inplay_simulate_inplay", "target": "backtest_inplay_extract_serve_probs", "relation": "calls", "confidence": "EXTRACTED", "source_file": "backtest_inplay.py", "source_location": "L201", "weight": 1.0}, {"source": "backtest_inplay_simulate_inplay", "target": "backtest_inplay_kelly_size", "relation": "calls", "confidence": "EXTRACTED", "source_file": "backtest_inplay.py", "source_location": "L243", "weight": 1.0}, {"source": "backtest_inplay_main", "target": "backtest_inplay_load_matches", "relation": "calls", "confidence": "EXTRACTED", "source_file": "backtest_inplay.py", "source_location": "L343", "weight": 1.0}, {"source": "backtest_inplay_main", "target": "backtest_inplay_build_elo", "relation": "calls", "confidence": "EXTRACTED", "source_file": "backtest_inplay.py", "source_location": "L346", "weight": 1.0}, {"source": "backtest_inplay_main", "target": "backtest_inplay_simulate_inplay", "relation": "calls", "confidence": "EXTRACTED", "source_file": "backtest_inplay.py", "source_location": "L355", "weight": 1.0}, {"source": "backtest_inplay_rationale_1", "target": "backtest_inplay_py", "relation": "rationale_for", "confidence": "EXTRACTED", "source_file": "backtest_inplay.py", "source_location": "L1", "weight": 1.0}, {"source": "backtest_inplay_rationale_79", "target": "backtest_inplay_extract_serve_probs", "relation": "rationale_for", "confidence": "EXTRACTED", "source_file": "backtest_inplay.py", "source_location": "L79", "weight": 1.0}, {"source": "backtest_inplay_rationale_128", "target": "backtest_inplay_parse_score", "relation": "rationale_for", "confidence": "EXTRACTED", "source_file": "backtest_inplay.py", "source_location": "L128", "weight": 1.0}, {"source": "backtest_inplay_rationale_181", "target": "backtest_inplay_simulate_inplay", "relation": "rationale_for", "confidence": "EXTRACTED", "source_file": "backtest_inplay.py", "source_location": "L181", "weight": 1.0}]}